<?xml version="1.0" encoding="UTF-8"?>
<objects serializationModel="Studio.02.00.00">
	<object class="AudioFile" id="{3e72ce9f-2a25-4227-ae1b-4fd4666cc546}">
		<property name="assetPath">
			<value>NewRobotVox2/JumpHeight.wav</value>
		</property>
		<property name="frequencyInKHz">
			<value>96</value>
		</property>
		<property name="channelCount">
			<value>2</value>
		</property>
		<property name="length">
			<value>2</value>
		</property>
		<relationship name="masterAssetFolder">
			<destination>{d70a43e6-65cf-44a4-9412-4df5a2b81596}</destination>
		</relationship>
	</object>
</objects>
